pydingo/__init__.py
pydingo/client.py
pydingo/client_stub.py
sts_pydingo-0.1.dist-info/METADATA
sts_pydingo-0.1.dist-info/WHEEL
sts_pydingo-0.1.dist-info/top_level.txt
sts_pydingo-0.1.dist-info/RECORD
