Metadata-Version: 2.1
Name: sts-pydingo
Version: 0.1
Summary: Device library
Home-page: UNKNOWN
Author: See-Through Scientific
Author-email: UNKNOWN
License: UNKNOWN
Platform: UNKNOWN
